py_vapid/__init__.py
py_vapid/__main__.py
py_vapid/jwt.py
py_vapid/main.py
py_vapid/utils.py
py_vapid/tests/.test_vapid.py.swp
py_vapid/tests/test_vapid.py
py_vapid-1.9.3.dist-info/METADATA
py_vapid-1.9.3.dist-info/WHEEL
py_vapid-1.9.3.dist-info/entry_points.txt
py_vapid-1.9.3.dist-info/licenses/LICENSE
py_vapid-1.9.3.dist-info/RECORD
