Metadata-Version: 2.4
Name: py-vapid
Version: 1.9.3
Summary: Simple VAPID header generation library
Project-URL: Homepage, https://github.com/mozilla-services/vapid
Author-email: JR Conlin <src+vapid@jrconlin.com>
License: MPL-2.0
License-File: LICENSE
Keywords: push,vapid,webpush
Classifier: Programming Language :: Python
Classifier: Programming Language :: Python :: 3
Classifier: Topic :: Internet :: WWW/HTTP
Requires-Dist: cryptography>=46
Provides-Extra: test
Requires-Dist: coverage; extra == 'test'
Requires-Dist: flake8; extra == 'test'
Requires-Dist: mock>=1.0; extra == 'test'
Requires-Dist: pytest; extra == 'test'
